{
  "project_info": {
    "project_number": "750266793979",
    "firebase_url": "https://task3-60aa6.firebaseio.com",
    "project_id": "task3-60aa6",
    "storage_bucket": "task3-60aa6.appspot.com"
  },
  "client": [
    {
      "client_info": {
        "mobilesdk_app_id": "1:750266793979:android:9a0f3367a90612967e555e",
        "android_client_info": {
          "package_name": "com.example.task3"
        }
      },
      "oauth_client": [
        {
          "client_id": "750266793979-kjmpi2n5g5vnelqkhbp3hpc5v7h3aomk.apps.googleusercontent.com",
          "client_type": 3
        }
      ],
      "api_key": [
        {
          "current_key": "AIzaSyC_jMavrh08VjJuXwtcUXDVRyxEpMPUICs"
        }
      ],
      "services": {
        "appinvite_service": {
          "other_platform_oauth_client": [
            {
              "client_id": "750266793979-kjmpi2n5g5vnelqkhbp3hpc5v7h3aomk.apps.googleusercontent.com",
              "client_type": 3
            }
          ]
        }
      }
    }
  ],
  "configuration_version": "1"
}